enderchest/__init__.py
enderchest/_version.py
enderchest/cli.py
enderchest/config.py
enderchest/craft.py
enderchest/enderchest.py
enderchest/filesystem.py
enderchest/gather.py
enderchest/instance.py
enderchest/inventory.py
enderchest/loggers.py
enderchest/place.py
enderchest/prompt.py
enderchest/py.typed
enderchest/remote.py
enderchest/shulker_box.py
enderchest/uninstall.py
enderchest/sync/__init__.py
enderchest/sync/file.py
enderchest/sync/rsync.py
enderchest/sync/sftp.py
enderchest/sync/utils.py
enderchest/test/__init__.py
enderchest/test/conftest.py
enderchest/test/mock_paramiko.py
enderchest/test/plugin.py
enderchest/test/test_break.py
enderchest/test/test_cli.py
enderchest/test/test_config.py
enderchest/test/test_craft.py
enderchest/test/test_gather.py
enderchest/test/test_instance.py
enderchest/test/test_inventory.py
enderchest/test/test_place.py
enderchest/test/test_sync.py
enderchest/test/test_sync_utils.py
enderchest/test/utils.py
enderchest/test/testing_files/__init__.py
enderchest/test/testing_files/enderchest.cfg
enderchest/test/testing_files/instgroups.json
enderchest/test/testing_files/launcher_profiles.json
enderchest/test/testing_files/lstat_cache.json
enderchest/test/testing_files/options.txt
enderchest/test/testing_files/version_manifest_v2.json
enderchest-0.1.7.dist-info/licenses/LICENSE
enderchest-0.1.7.dist-info/METADATA
enderchest-0.1.7.dist-info/WHEEL
enderchest-0.1.7.dist-info/entry_points.txt
enderchest-0.1.7.dist-info/top_level.txt
enderchest-0.1.7.dist-info/RECORD
