Metadata-Version: 2.4
Name: enderchest
Version: 0.1.7
Summary: syncing and linking for all your Minecraft instances
Home-page: https://github.com/OpenBagTwo/EnderChest
Author: Gili "OpenBagTwo" Barlev
License: GPL v3
Requires-Python: >=3.10
License-File: LICENSE
Requires-Dist: semantic-version>=2.7
Requires-Dist: pathvalidate>=2.5
Provides-Extra: test
Requires-Dist: pytest>=7; extra == "test"
Requires-Dist: coverage>=7; extra == "test"
Provides-Extra: sftp
Requires-Dist: paramiko>=3.3; extra == "sftp"
Dynamic: author
Dynamic: description
Dynamic: description-content-type
Dynamic: home-page
Dynamic: license
Dynamic: license-file
Dynamic: provides-extra
Dynamic: requires-dist
Dynamic: requires-python
Dynamic: summary
